src/memory/data_mem.v
module data_mem #(
    parameter XLEN = 32,
    parameter DEPTH = 256
    )(
        input clk,
        input MemRead,
        input MemWrite,
        input [XLEN-1:0] write_data,
        input [XLEN-1:0] addr,
        output reg [XLEN-1:0] read_data
    );
    // BITS FOR ADDRESSING
    localparam ADDR_WIDTH = $clog2(DEPTH);

    // MEMORY DECLARATION
    reg [XLEN-1:0] memory [0:DEPTH-1];

    // SYNCHRONOUS WRITE
    always @(posedge clk) begin
        if(MemWrite)
            memory[addr[ADDR_WIDTH+1:2]] <= write_data; 
    end

    // COMBINATIONAL READ
    always @(*) begin
        if(MemRead)
            read_data = memory[addr[ADDR_WIDTH+1:2]]; 
        else 
            read_data = {XLEN{1'b0}};
    end

                            // NOTE
    // 1 Byte = 8 bits
    // 1 Word = 32 Bits = 4 Bytes
    // Each Address points to 1 Byte
    // Addr 1000 is Byte 0
    //      1001 => Byte 1
    //      1002 => Byte 2
    //      1003 => Byte 3
    // Index = addr / 4
    // We use addr[31:2] because we currently support only word-aligned accesses (LW/SW).
    // Each memory entry is 32 bits (4 bytes), so we divide byte address by 4.
    // The lower 2 bits (addr[1:0]) are ignored since they are always 00 for word alignment.
    //
    // NOTE:
    // If we implement LB (Load Byte) or LH (Load Halfword),
    // we cannot ignore addr[1:0] anymore.
    // Those bits are required to select the correct byte or halfword inside the 32-bit word.                                

endmodule

full_adder_n_bit.v

//////////////////////////////////////////////////////////////////////////////////
// Company: 
// Engineer: 
// 
// Create Date: 01/14/2026 11:13:05 AM
// Design Name: 
// Module Name: 4_bit_adder
// Project Name: 
// Target Devices: 
// Tool Versions: 
// Description: 
// 
// Dependencies: 
// 
// Revision:
// Revision 0.01 - File Created
// Additional Comments:
// 
//////////////////////////////////////////////////////////////////////////////////


module full_adder_n_bit #(
	parameter WIDTH = 4
)(
    input [WIDTH-1:0] a,
    input [WIDTH-1:0] b,
    input c_in,
    output c_out,
    output [WIDTH-1:0] sum
    );
    
    assign {c_out,sum} = a + b + c_in;     

    
    //logic c1,c2,c3;
    
    //full_adder f1(.a(a[0]), .b(b[0]), .c(c_in), .sum(sum[0]), .carry(c1));
    //full_adder f2(.a(a[1]), .b(b[1]), .c(c1), .sum(sum[1]), .carry(c2));
    //full_adder f3(.a(a[2]), .b(b[2]), .c(c2), .sum(sum[2]), .carry(c3));
    //full_adder f4(.a(a[3]), .b(b[3]), .c(c3), .sum(sum[3]), .carry(c_out));    
endmodule

ALU_n_bit.v

//////////////////////////////////////////////////////////////////////////////////
// Company: 
// Engineer: 
// 
// Create Date: 01/16/2026 03:26:46 PM
// Design Name: 
// Module Name: ALU_n_bit
// Project Name: 
// Target Devices: 
// Tool Versions: 
// Description: 
// 
// Dependencies: 
// 
// Revision:
// Revision 0.01 - File Created
// Additional Comments:
// 
//////////////////////////////////////////////////////////////////////////////////


module ALU_n_bit#(
    parameter WIDTH = 32
)(
    input [3:0] op_code,
    input [WIDTH-1:0] a,
    input [WIDTH-1:0] b,
    input c_in,
    output reg [WIDTH-1:0] answer,
    output reg c_out,
    output reg zero,
    output reg negative,
    output reg overflow
);
    
    wire [WIDTH-1:0] add_sol;
//  wire [WIDTH-1:0] sub_sol;
    wire [WIDTH-1:0] inc_sol;
    wire [WIDTH-1:0] dec_sol;
    
    wire [WIDTH-1:0] and_sol;
    wire [WIDTH-1:0] or_sol;
    wire [WIDTH-1:0] xor_sol;
    wire [WIDTH-1:0] not_sol;
    
    wire [WIDTH-1:0] left_shift_logical_sol;
    wire [WIDTH-1:0] right_shift_logical_sol;

    wire [WIDTH-1:0] right_shift_arithmetic_sol;
    wire [WIDTH-1:0] SLT;

//  wire sub_in;
//  wire sub_out;
//  wire add_in;
    wire add_out;
    
//FOR SUBTRACTING LOGIC
    wire sub;
    wire [WIDTH-1:0] b_mux;
    wire carry_mux;
    wire overflow_wire;


    assign sub = (op_code == 4'd1);
    assign b_mux = sub? ~b : b;                 // NOT IS 1'S COMPLEMENT
    assign carry_mux = sub? 1'b1 : c_in;        // SUB = A + (~B + 1)


/*

        WHY OVERFLOW REQ?
        FOR SIGNED INTEGERS EX: 4BIT SIGNED NUMBER EXISTS FROM -8 TO +7
        IF A + B IS ASKED FOR A=0100  B=0101    {A=4, B=5}
        SUM WILL BE 1001 {9} WHICH WILL BE -1 IN SIGNED NUMBERS
        SO IT WILL BE AN OVERFLOW

*/


//  assign sub_in = c_in;
//  assign add_in = c_in;
    
    full_adder_n_bit #(
    .WIDTH(WIDTH)
    )f1(
        .a(a),
        .b(b_mux),
        .c_in(carry_mux),
        .c_out(add_out),
        .sum(add_sol)
    );

    assign overflow_wire = ((a[WIDTH-1] == b_mux[WIDTH-1]) && (a[WIDTH-1] != add_sol[WIDTH-1]));
/*    full_subtractor_n_bit f2#(
    .WIDTH(WIDTH)                           // INDUSTRIES DO NOT USE SEPERATE SUBTRACT BLOCK 
    )(
        .a(a),
        .b(b),
        .difference(sub_sol),
        .borrow_in(c_in),
        .borrow_out(sub_out)
    );
*/
    assign inc_sol = a + 1;
    assign dec_sol = a - 1;
    
    assign and_sol = a & b;
    assign or_sol = a | b;
    assign xor_sol = a ^ b;
    assign not_sol = ~a;
    
    assign left_shift_logical_sol = a << b[4:0];
    assign right_shift_logical_sol = a >> b[4:0];
    
    assign right_shift_arithmetic_sol = $signed(a) >>> b[4:0];
    assign SLT = ($signed(a) < $signed(b))? 32'd1 : 32'd0;
    always @(*) begin
    
    overflow = 1'b0;
    answer = {WIDTH{1'b0}};
    c_out  = 1'b0;

    case(op_code)

        4'd0,
        4'd1 : begin 
                    answer = add_sol;
                    c_out = add_out;
                    overflow = overflow_wire;
               end
        4'd2 : answer = inc_sol;
	    4'd3 : answer = dec_sol;	                
        4'd4 : answer = and_sol;
        4'd5 : answer = or_sol;
        4'd6 : answer = xor_sol;
        4'd7 : answer = not_sol;       
        4'd8 : answer = left_shift_logical_sol;
        4'd9 : answer = right_shift_logical_sol;
        4'd10: answer = right_shift_arithmetic_sol;
        4'd11: answer = SLT;
        default: begin
                    answer = {WIDTH{1'b0}};
                    c_out  = 1'b0;
                 end
        //1 for bitwise or
        //2 for bitwise and
        //3 for bitwise xor
        //4 for adder
        //5 for subtracting
     endcase

    zero = (answer == {WIDTH{1'b0}});
    negative = answer[WIDTH-1];

     end
endmodule

alu_control.v
module alu_control(
    input [2:0] ALU_OP,
    input [2:0] funct3,
    input [6:0] funct7,
    output reg [3:0] alu_op
);

localparam ADD = 4'd0;
localparam SUB = 4'd1;
localparam AND = 4'd4;
localparam OR  = 4'd5;
localparam XOR = 4'd6;
localparam SLL = 4'd8;
localparam SRL = 4'd9;
localparam SRA = 4'd10;
localparam SLT = 4'd11;
    
	always @(*) begin
	    case (ALU_OP)
		3'd0: begin
			case(funct3) 
				3'b000 : alu_op = ADD;
				3'b001 : alu_op = SLL;
				3'b010 : alu_op = SLT;
				3'b100 : alu_op = XOR;
				3'b110 : alu_op = OR ;
				3'b111 : alu_op = AND;
				3'b101 : begin
						if (funct7 == 7'b0000000)
							alu_op = SRL;
						else if(funct7 == 7'b0100000)
							alu_op = SRA;
					end
			endcase						
		end
		3'd1: begin									// B
			case(funct3) 
				3'b000 : alu_op = SUB;				//BEQ
				3'b001 : alu_op = SUB;
				3'b100 : alu_op = SUB;
				3'b101 : alu_op = SUB;
				3'b110 : alu_op = SUB;
				3'b111 : alu_op = SUB;
			endcase
		end 
		3'd2: begin
		    case({funct7, funct3})
		            10'b0000000000: alu_op = ADD;  // ADD
		            10'b0100000000: alu_op = SUB;  // SUB
		            10'b0000000111: alu_op = AND;
		            10'b0000000110: alu_op = OR;
		            10'b0000000100: alu_op = XOR;
		            10'b0000000001: alu_op = SLL;
		            10'b0000000101: alu_op = SRL;
		            10'b0100000101: alu_op = SRA;
		            10'b0000000010: alu_op = SLT;
		            default : alu_op = ADD;
		    endcase
		end
		
		3'b3: alu_op = ADD;
		
		default : alu_op = ADD;
	    endcase
	 end
endmodule

imm_gen.v
module imm_gen #(
    parameter XLEN = 32
)(
    input [31:0] instr,
    output reg [XLEN-1:0] imm_out
);
    wire [6:0] op_code;         // 7 BIT OPCODE FOR CHECKING WHTHER ITS I, R, LOAD, STORE, BRANCH, JUMP, ETC
    assign op_code = instr[6:0];

    always @(*) begin
        case(op_code)
            // I-TYPE (ADDI, LW)
            7'b0010011,     //ADDI
            7'b0000011:
                //imm_out = {{20{instr[31]}}, instr[31:20]};

                imm_out = {{(XLEN-12){instr[31]}}, instr[31:20]};

                // IMM[11:0], RS1, FUNCT3, RD, OP_CODE
                // HERE IMM IS 12 BIT, BUT FOR ALU IT EXPECTS 32 BIT VALUE SO WE DID LIKE THIS
                // EX:- 111111111111 IS -1(1ST DIGIT IS 1 SO THE NUMBER IS NEGATIVE, TO FIND ITS MAGNITUDE TAKE 1'S COMPLEMENT AND ADD 1 FOR THIS EX:-YOU WILL GET 1 SO THE ACTUAL NUMBER IS -1)
                // FOR 32 BIT IF YOU GIVE  00000000000000000000 111111111111 IT WILL BECOME 4095
                // THEN THE ACTUAL CORRECT NUMBER WILL BE 11111111111111111111 111111111111
            
            // S-TYPE       EX:- SW x5, 8(x1)   =>      Memmory[x1+8] = x5      =>      base register is x1 and data to store is x5
            7'b0100011:
                // IMM[11:5], RS2, RS1, FUNCT3, IMM[4:0], OP_CODE
                // HERE SPLITTING IS HAPPENED CUZ RS2 OCCUPIED SOME SPACE(COMPARE WITH I TYPE)
                // BUT WE GOT SPACE IN RD REGION TO UTILISE THE SPACE REMAINING PART OF IMM WENT TO THERE
                // (SMART ENCODING SYSTEM)
                // FUNCT3 TELLS SUBPART OF THAT OP_CODE FAMILY EX:- FOR LOAD FAM-LB, LH, LW & FOR STORE FAM-SB, SH, SW
                // LW x8, 4(x2)         =>          x2=1000, given Mem[1004]=55, then x8=55
                // SW x8, 4(x2)         =>          x2=1000, given x8 is 55, then Mem[1004]=x8
                imm_out = {{(XLEN-12){instr[31]}}, instr[31:25], instr[11:7]};
            
            // B-TYPE 
            7'b1100011:
                imm_out = {
                            {{(XLEN-13){instr[31]}}},
                            instr[31],
                            instr[7],
                            instr[30:25],
                            instr[11:8],
                            1'b0
                            };

            //  U-TYPE
            //  LUI(LOAD UPPER IMMEDIATE), AUIPC
            7'b0110111,
            7'b0010111:
                imm_out = {
                            instr[31:12],
                            12'b0
                            };
            
            // J-TYPE 
            7'b1101111:                 // JAL
                imm_out = {
                            {{(XLEN-21){instr[31]}}},
                            instr[31],
                            instr[19:12],
                            instr[20],
                            instr[30:21],
                            1'b0
                            };

            7'b1100111:
                imm_out = {
                            {{(XLEN-12){instr[31]}}},
                            instr[31:20]
                            };
                            
            default:
                imm_out = {XLEN{1'b0}};
        endcase
    end
endmodule

register.v
module register_file #(
    parameter REG_DEPTH = 32,
    parameter DATA_WIDTH = 32,
    parameter ADDR_WIDTH = $clog2(REG_DEPTH)  // HERE C IS CEILING (OPPOSITE TO STEP)
)(
    input clk,
    input rst_n,                // Reset is included for safe initialization.
// In industry, datapath registers may avoid reset for area/power optimization,
// but control logic and PC typically use reset.
                        
    input reg_write,
    input [ADDR_WIDTH-1:0] rd,              // DESTINATION REGISTER FOR WRITING DATA
    input [DATA_WIDTH-1:0] write_data,     
    
    input [ADDR_WIDTH-1:0] rs1,             // SOURCE REGISTER 1 FOR READING DATA
    input [ADDR_WIDTH-1:0] rs2,             // SOURCE REGISTER 2 FOR READING DATA

    output [DATA_WIDTH-1:0] read_data1,
    output [DATA_WIDTH-1:0] read_data2
);

        // REGISTER
reg [DATA_WIDTH-1:0] regs [0:REG_DEPTH-1];

        // WRITE LOGIC 
always @(posedge clk) begin
    if(!rst_n) begin       
        for(integer i =0; i<REG_DEPTH; i++)
            regs[i] <= {DATA_WIDTH{1'b0}};
    end
    else begin
        if(reg_write && rd!=0) 
            regs[rd] <= write_data;  
    end
end

        // READ LOGIC
assign read_data1 = (rs1 == 0)? {DATA_WIDTH{1'b0}}: regs[rs1];
assign read_data2 = (rs2 == 0)? {DATA_WIDTH{1'b0}}: regs[rs2];

endmodule

control_unit.v
module control_unit (
    input [6:0] op_code,

    output reg RegWrite,
    output reg MemRead,
    output reg MemWrite,
    output reg ALUSrc,
    output reg MemToReg,
    output reg Branch,
    output reg Jump,
    output reg [2:0] ALU_OP 
);

always @(*) begin
    case(op_code)
        7'b0010011: begin           // I-type ADDI
            RegWrite = 1;
            MemRead  = 0;
            MemWrite = 0;
            ALUSrc   = 1;   // USE IMMEDIATE
            MemToReg = 0;   // TAKE ALU RESULT
            Branch   = 0;
            Jump     = 0;
            ALU_OP   = 3'd0;
        end    

        7'b0000011: begin           // I-type LW
            RegWrite = 1;
            MemRead  = 1;
            MemWrite = 0;
            ALUSrc   = 1;   
            MemToReg = 1;   
            Branch   = 0;
            Jump     = 0;
            ALU_OP   = 3'd3;
        end    

        7'b0100011: begin           // S-type SW
            RegWrite = 0;
            MemRead  = 0;
            MemWrite = 1;
            ALUSrc   = 1;   
            MemToReg = 0;   
            Branch   = 0;
            Jump     = 0;
            ALU_OP   = 3'd3;
        end    

        7'b1100011: begin           // B-type BEQ
            RegWrite = 0;
            MemRead  = 0;
            MemWrite = 0;
            ALUSrc   = 0;   
            MemToReg = 0;   
            Branch   = 1;
            Jump     = 0;
            ALU_OP   = 3'd1;
        end  

        7'b0110011: begin           // R-type
            RegWrite = 1;
            MemRead  = 0;
            MemWrite = 0;
            ALUSrc   = 0;   
            MemToReg = 0;   
            Branch   = 0;
            Jump     = 0;
            ALU_OP   = 3'd2;
        end

        7'b0110111: begin           // U-TYPE => LUI
            RegWrite = 1;
            MemRead  = 0;
            MemWrite = 0;
            ALUSrc   = 1;   
            MemToReg = 0;   
            Branch   = 0;
            Jump     = 0;
            ALU_OP   = 3'd3;
        end

        7'b0010111: begin           // U-TYPE => AUIPC
            RegWrite = 1;
            MemRead  = 0;
            MemWrite = 0;
            ALUSrc   = 1;   
            MemToReg = 0;   
            Branch   = 0;
            Jump     = 0;
            ALU_OP   = 3'd3;
        end                 

        7'b1101111: begin           // J-TYPE
            RegWrite = 1;
            MemRead  = 0;
            MemWrite = 0;
            ALUSrc   = 1;   
            MemToReg = 0;   
            Branch   = 0;
            Jump     = 1;
            ALU_OP   = 3'd3;
        end

        7'b1100111: begin
            RegWrite = 1;
            MemRead  = 0;
            MemWrite = 0;
            ALUSrc   = 0;   
            MemToReg = 0;   
            Branch   = 0;
            Jump     = 1;
            ALU_OP   = 3'd3;
        end

        default: begin
            RegWrite = 0;
            MemRead  = 0;
            MemWrite = 0;
            ALUSrc   = 0;   
            MemToReg = 0;   
            Branch   = 0;
            Jump     = 0;
            ALU_OP   = 3'd0;
        end
    endcase
end
endmodule

instruction_mem.v
module instruction_memory #(
    parameter XLEN = 32,
    parameter DEPTH = 256
)(
    input [XLEN-1:0] addr,
    output [31:0] instr
);

    localparam ADDR_WIDTH = $clog2(DEPTH);

    // INSTRUCTION MEMORY (EACH INSTRUCTION = 32 BITS)
    reg [XLEN-1:0] instr_memory [0:DEPTH-1];

/*
    initial begin
        instr_memory[0]  = 32'h00A00093;
        instr_memory[1]  = 32'h00500113;
        instr_memory[2]  = 32'h002081B3;
        instr_memory[3]  = 32'h40208233;
        instr_memory[4]  = 32'h0020F2B3;
        instr_memory[5]  = 32'h0020E333;
        instr_memory[6]  = 32'h0020C3B3;
        instr_memory[7]  = 32'h00209433;
        instr_memory[8]  = 32'h0020D4B3;
        instr_memory[9]  = 32'h4020D533;
        instr_memory[10] = 32'h001125B3;
    end
*/

    assign instr = instr_memory[addr[ADDR_WIDTH+1:2]];

endmodule

RV32I.v
module rv32i_single_cycle #(
    parameter XLEN = 32
)(
    input clk,
    input rst_n
);

    // PC 
    reg [XLEN-1:0] PC;
    wire [XLEN-1:0] PC_next;

    // INSTRUCTION _MEMORY
    wire [XLEN-1:0] instr;

    instruction_memory imem(
        .addr(PC),
        .instr(instr)
    );

    // DECODE
    wire [6:0] opcode   = instr[6:0];
    wire [4:0] rd       = instr[11:7];
    wire [2:0] funct3   = instr[14:12];
    wire [4:0] rs1      = instr[19:15];
    wire [4:0] rs2      = instr[24:20];
    wire [6:0] funct7    = instr[31:25];

    // CONTROL UNIT 
    wire RegWrite;
    wire MemRead;
    wire MemWrite;
    wire ALUSrc;
    wire MemToReg;
    wire Branch;
    wire Jump;
    wire [2:0] ALU_OP;

    control_unit cu(
        .op_code(opcode),
        .RegWrite(RegWrite),
        .MemRead(MemRead),
        .MemWrite(MemWrite),
        .ALUSrc(ALUSrc),
        .MemToReg(MemToReg),
        .Branch(Branch),
        .ALU_OP(ALU_OP),
        .Jump(Jump)
    );

    // REGISTER
    wire [XLEN-1:0] write_data;
    wire [XLEN-1:0] read_data1;
    wire [XLEN-1:0] read_data2;

    register_file rf(
        .clk(clk),
        .rst_n(rst_n),
        .reg_write(RegWrite),
        .rd(rd),
        .write_data(write_data),
        .rs1(rs1),
        .rs2(rs2),
        .read_data1(read_data1),
        .read_data2(read_data2)
    );

    // IMMEDIATE GENERATOR
    wire [XLEN-1:0] imm_out;

    imm_gen ig (
        .instr(instr),
        .imm_out(imm_out)
    );
    
    // ALU CONTROL LOGIC
    wire [3:0] alu_op;
    alu_control ac(
        .ALU_OP(ALU_OP),
        .funct3(funct3),
        .funct7(funct7),
        .alu_op(alu_op)
    );

    // ALU
    wire [XLEN-1:0] alu_input_b; 
    wire [XLEN-1:0] alu_input_a; 
    wire [XLEN-1:0] alu_result;
    wire zero_flag;
    assign alu_input_a = 
            (Jump)? (PC) :
            (opcode == 7'b0010111)? (PC) : 
            (opcode == 7'b0110111)? 32'b0: 
             read_data1;
    assign alu_input_b = (Jump)? 32'd4 : (ALUSrc)? (imm_out) : (read_data2);
    wire carry_out;
    wire negative;
    wire overflow;

    ALU_n_bit #(
        .WIDTH(32)
    ) alu (
        .op_code(alu_op),
        .a(alu_input_a),
        .b(alu_input_b),
        .c_in(1'b0),
        .answer(alu_result),
        .c_out(carry_out),
        .zero(zero_flag),
        .negative(negative),
        .overflow(overflow)
    );

    // DATA MEMORY 
    wire [XLEN-1:0] mem_data; 
    data_mem dm(
        .clk(clk),
        .MemRead(MemRead),
        .MemWrite(MemWrite),
        .write_data(read_data2),        // CUZ, [SW x8, 4(x2)] => Memory[x2 + 4] = x8
        .addr(alu_result),
        .read_data(mem_data)
    );

    // WRITE BACK MUX
    assign write_data = (MemToReg)? mem_data : alu_result;
    reg branch_taken;
    always @(*) begin
        case(funct3)
            3'b000 : branch_taken = zero_flag;
            3'b001 : branch_taken = ~zero_flag;
            3'b100 : branch_taken = negative ^ overflow;
            3'b101 : branch_taken = ~(negative ^ overflow);
            3'b110 : branch_taken = ~carry_out;
            3'b111 : branch_taken = carry_out; 
       	    default: branch_taken = 0;
        endcase
    end

    //PC UPDATE LOGIC
    assign PC_next = (opcode == 7'b1100111)? (read_data1+imm_out) & (32'hFFFFFFFE)  : 
                        ((Jump | (Branch & branch_taken))? (PC + imm_out) : (PC + 4));

    always @(posedge clk) begin
        if(!rst_n)
            PC <= 0;
        else
            PC <= PC_next; 
    end

endmodule

test_lw_sw.v
module test_lw_sw;
    reg clk;
    reg rst_n;
    rv32i_single_cycle rv (
        .clk(clk),
        .rst_n(rst_n)
    );
    initial begin
        clk = 0;
        rst_n = 0;
        rv.imem.instr_memory[0] = 32'h00a00093; // ADDI x1, x0, 10
        rv.imem.instr_memory[1] = 32'h01002023; // SW x1, 16(x0)
        rv.imem.instr_memory[2] = 32'h01002103; // LW x2, 16(x0)
        #15 rst_n = 1;
        #60;
        $display("x1 = %d", rv.rf.regs[1]);
        $display("x2 = %d", rv.rf.regs[2]);
        $display("mem[0] = %d", rv.dm.memory[0]);
        $display("mem[4] = %d", rv.dm.memory[4]);
        $display("PC = %d", rv.PC);
        $finish;
    end
    always #5 clk = ~clk;
endmodule

test_lw_sw.vcd
$date
	Sat May 16 14:37:40 2026
$end
$version
	Icarus Verilog
$end
$timescale
	1s
$end
$scope module test_lw_sw $end
$var reg 1 ! clk $end
$var reg 1 " rst_n $end
$scope module rv $end
$var wire 1 ! clk $end
$var wire 1 " rst_n $end
$var wire 1 # zero_flag $end
$var wire 32 $ write_data [31:0] $end
$var wire 5 % rs2 [4:0] $end
$var wire 5 & rs1 [4:0] $end
$var wire 32 ' read_data2 [31:0] $end
$var wire 32 ( read_data1 [31:0] $end
$var wire 5 ) rd [4:0] $end
$var wire 1 * overflow $end
$var wire 7 + opcode [6:0] $end
$var wire 1 , negative $end
$var wire 32 - mem_data [31:0] $end
$var wire 32 . instr [31:0] $end
$var wire 32 / imm_out [31:0] $end
$var wire 7 0 funct7 [6:0] $end
$var wire 3 1 funct3 [2:0] $end
$var wire 1 2 carry_out $end
$var wire 32 3 alu_result [31:0] $end
$var wire 4 4 alu_op [3:0] $end
$var wire 32 5 alu_input_b [31:0] $end
$var wire 32 6 alu_input_a [31:0] $end
$var wire 1 7 RegWrite $end
$var wire 32 8 PC_next [31:0] $end
$var wire 1 9 MemWrite $end
$var wire 1 : MemToReg $end
$var wire 1 ; MemRead $end
$var wire 1 < Jump $end
$var wire 1 = Branch $end
$var wire 3 > ALU_OP [2:0] $end
$var wire 1 ? ALUSrc $end
$var parameter 32 @ XLEN $end
$var reg 32 A PC [31:0] $end
$var reg 1 B branch_taken $end
$scope module ac $end
$var wire 3 C funct3 [2:0] $end
$var wire 7 D funct7 [6:0] $end
$var wire 3 E ALU_OP [2:0] $end
$var parameter 4 F ADD $end
$var parameter 4 G AND $end
$var parameter 4 H OR $end
$var parameter 4 I SLL $end
$var parameter 4 J SLT $end
$var parameter 4 K SRA $end
$var parameter 4 L SRL $end
$var parameter 4 M SUB $end
$var parameter 4 N XOR $end
$var reg 4 O alu_op [3:0] $end
$upscope $end
$scope module alu $end
$var wire 32 P a [31:0] $end
$var wire 32 Q and_sol [31:0] $end
$var wire 32 R b [31:0] $end
$var wire 1 S c_in $end
$var wire 32 T not_sol [31:0] $end
$var wire 4 U op_code [3:0] $end
$var wire 32 V or_sol [31:0] $end
$var wire 1 W overflow_wire $end
$var wire 32 X xor_sol [31:0] $end
$var wire 1 Y sub $end
$var wire 32 Z right_shift_logical_sol [31:0] $end
$var wire 32 [ right_shift_arithmetic_sol [31:0] $end
$var wire 32 \ left_shift_logical_sol [31:0] $end
$var wire 32 ] inc_sol [31:0] $end
$var wire 32 ^ dec_sol [31:0] $end
$var wire 1 _ carry_mux $end
$var wire 32 ` b_mux [31:0] $end
$var wire 32 a add_sol [31:0] $end
$var wire 1 b add_out $end
$var wire 32 c SLT [31:0] $end
$var parameter 32 d WIDTH $end
$var reg 32 e answer [31:0] $end
$var reg 1 2 c_out $end
$var reg 1 , negative $end
$var reg 1 * overflow $end
$var reg 1 # zero $end
$scope module f1 $end
$var wire 32 f a [31:0] $end
$var wire 32 g b [31:0] $end
$var wire 1 _ c_in $end
$var wire 32 h sum [31:0] $end
$var wire 1 b c_out $end
$var parameter 32 i WIDTH $end
$upscope $end
$upscope $end
$scope module cu $end
$var wire 7 j op_code [6:0] $end
$var reg 1 ? ALUSrc $end
$var reg 3 k ALU_OP [2:0] $end
$var reg 1 = Branch $end
$var reg 1 < Jump $end
$var reg 1 ; MemRead $end
$var reg 1 : MemToReg $end
$var reg 1 9 MemWrite $end
$var reg 1 7 RegWrite $end
$upscope $end
$scope module dm $end
$var wire 1 ; MemRead $end
$var wire 1 9 MemWrite $end
$var wire 32 l addr [31:0] $end
$var wire 1 ! clk $end
$var wire 32 m write_data [31:0] $end
$var parameter 32 n ADDR_WIDTH $end
$var parameter 32 o DEPTH $end
$var parameter 32 p XLEN $end
$var reg 32 q read_data [31:0] $end
$upscope $end
$scope module ig $end
$var wire 7 r op_code [6:0] $end
$var wire 32 s instr [31:0] $end
$var parameter 32 t XLEN $end
$var reg 32 u imm_out [31:0] $end
$upscope $end
$scope module imem $end
$var wire 32 v addr [31:0] $end
$var wire 32 w instr [31:0] $end
$var parameter 32 x ADDR_WIDTH $end
$var parameter 32 y DEPTH $end
$var parameter 32 z XLEN $end
$upscope $end
$scope module rf $end
$var wire 1 ! clk $end
$var wire 5 { rd [4:0] $end
$var wire 1 7 reg_write $end
$var wire 5 | rs1 [4:0] $end
$var wire 5 } rs2 [4:0] $end
$var wire 1 " rst_n $end
$var wire 32 ~ write_data [31:0] $end
$var wire 32 !" read_data2 [31:0] $end
$var wire 32 "" read_data1 [31:0] $end
$var parameter 32 #" ADDR_WIDTH $end
$var parameter 32 $" DATA_WIDTH $end
$var parameter 32 %" REG_DEPTH $end
$scope begin $ivl_for_loop0 $end
$var integer 32 &" i [31:0] $end
$upscope $end
$upscope $end
$upscope $end
$upscope $end
$enddefinitions $end
$comment Show the parameter values. $end
$dumpall
b100000 %"
b100000 $"
b101 #"
b100000 z
b100000000 y
b1000 x
b100000 t
b100000 p
b100000000 o
b1000 n
b100000 i
b100000 d
b110 N
b1 M
b1001 L
b1010 K
b1011 J
b1000 I
b101 H
b100 G
b0 F
b100000 @
$end
#0
$dumpvars
bx &"
bx ""
bx !"
b0 ~
bx }
bx |
bx {
bx w
bx v
bx u
bx s
bx r
b0 q
bx m
b0 l
bx k
bx j
bx h
bx g
bx f
b0 e
b0x c
xb
bx a
bx `
x_
bx ^
bx ]
bx \
bx [
bx Z
xY
bx X
xW
bx V
bx U
bx T
0S
bx R
bx Q
bx P
bx O
bx E
bx D
bx C
0B
bx A
x?
bx >
x=
x<
x;
x:
x9
bx 8
x7
bx 6
bx 5
bx 4
b0 3
02
bx 1
bx 0
bx /
bx .
b0 -
0,
bx +
0*
bx )
bx (
bx '
bx &
bx %
b0 $
1#
0"
0!
$end
#5
0W
b1010 a
b1010 h
0b
b1010 X
b11111111111111111111111111111111 T
b1 c
b1 ]
b11111111111111111111111111111111 ^
b0 [
b0 6
b0 P
b0 f
b1010 $
b1010 ~
b0 Q
b1010 V
b0 \
b0 Z
b0 '
b0 m
b0 !"
b0 (
b0 ""
0,
0#
0*
02
b1010 3
b1010 e
b1010 l
b1010 `
b1010 g
0_
b1010 5
b1010 R
0Y
b0 4
b0 O
b0 U
0B
b100 8
b0 >
b0 E
b0 k
0<
0=
0:
1?
09
0;
17
b10011 r
b0 0
b0 D
b1010 %
b1010 }
b0 &
b0 |
b0 1
b0 C
b1 )
b1 {
b10011 +
b10011 j
b1010 /
b1010 u
b101000000000000010010011 .
b101000000000000010010011 s
b101000000000000010010011 w
b0 A
b0 v
b100000 &"
1!
#10
0!
1"
#15
b100 a
b100 h
b1 $
b1 ~
b100 V
b100 X
b100 `
b100 g
b1010 '
b1010 m
b1010 !"
b1 3
b1 e
b1 l
b100 5
b100 R
b1011 4
b1011 O
b1011 U
19
07
b100011 r
b1 %
b1 }
b10 1
b10 C
b100 )
b100 {
b100011 +
b100011 j
b100 /
b100 u
b1000 8
b100000010001000100011 .
b100000010001000100011 s
b100000010001000100011 w
b100 A
b100 v
1!
#20
0!
#25
b100 a
b100 h
b1 3
b1 e
b1 l
b100 V
b100 X
b100 `
b100 g
b0 '
b0 m
b0 !"
b1010 $
b1010 ~
b1010 -
b1010 q
b100 5
b100 R
1:
09
1;
17
b11 r
b100 %
b100 }
b10 )
b10 {
b11 +
b11 j
b100 /
b100 u
b1100 8
b10000000010000100000011 .
b10000000010000100000011 s
b10000000010000100000011 w
b1000 A
b1000 v
1!
#30
0!
#35
b1000 Q
b11111111111111111111111111110101 T
b0 c
b1011 ]
b1001 ^
b101000000000 \
b1010 6
b1010 P
b1010 f
b10010 a
b10010 h
b1010 V
b10 X
b1000 `
b1000 g
b1010 (
b1010 ""
b1010 3
b1010 e
b1010 l
b1010 $
b1010 ~
b0 -
b0 q
b1000 5
b1000 R
b101 4
b101 O
b101 U
1B
0:
0;
b10011 r
b1000 %
b1000 }
b10 &
b10 |
b110 1
b110 C
b100 )
b100 {
b10011 +
b10011 j
b1000 /
b1000 u
b10000 8
b100000010110001000010011 .
b100000010110001000010011 s
b100000010110001000010011 w
b1100 A
b1100 v
1!
#40
0!
#45
b11001 a
b11001 h
b101 $
b101 ~
b1010 Q
b1111 V
b101 X
b1111 `
b1111 g
b1010000000000000000 \
b1 c
b101 3
b101 e
b101 l
b1111 5
b1111 R
b110 4
b110 O
b110 U
0B
b1111 %
b1111 }
b1 &
b1 |
b100 1
b100 C
b101 )
b101 {
b1111 /
b1111 u
b10100 8
b111100001100001010010011 .
b111100001100001010010011 s
b111100001100001010010011 w
b10000 A
b10000 v
1!
#50
0!
#55
b1011 a
b1011 h
b10100 $
b10100 ~
b0 Q
b1011 V
b1011 X
b1 `
b1 g
b10100 \
b101 Z
b101 [
b0 c
b1010 '
b1010 m
b1010 !"
b10100 3
b10100 e
b10100 l
b1 5
b1 R
b1000 4
b1000 O
b1000 U
1B
b1 %
b1 }
b10 &
b10 |
b1 1
b1 C
b110 )
b110 {
b1 /
b1 u
b11000 8
b100010001001100010011 .
b100010001001100010011 s
b100010001001100010011 w
b10100 A
b10100 v
1!
#60
0!
#65
b101 $
b101 ~
b101 3
b101 e
b101 l
b1001 4
b1001 O
b1001 U
b1 &
b1 |
b101 1
b101 C
b111 )
b111 {
b11100 8
b100001101001110010011 .
b100001101001110010011 s
b100001101001110010011 w
b11000 A
b11000 v
1!
